{
  "products": [
    {
      "image": "/images/product_starwars1.png",
      "title": "Caneca do starwars",
      "price": "60.00"
    },
    {
      "image": "/images/product_starwars2.png",
      "title": "Boneca do starwars",
      "price": "60.00"
    },
    {
      "image": "/images/product_starwars3.png",
      "title": "Action figure do starwars",
      "price": "60.00"
    },
    {
      "image": "/images/product_starwars4.png",
      "title": "Action figure do starwars",
      "price": "60.00"
    },
    {
      "image": "/images/product_starwars5.png",
      "title": "Action figure do starwars",
      "price": "60.00"
    },
    {
      "image": "/images/product_starwars6.png",
      "title": "Action figure do starwars",
      "price": "60.00"
    }
  ]
}